setup.cfg
setup.py
django_rest_autogen/__init__.py
django_rest_autogen/core.py
django_rest_autogen/registration.py
django_rest_autogen.egg-info/PKG-INFO
django_rest_autogen.egg-info/SOURCES.txt
django_rest_autogen.egg-info/dependency_links.txt
django_rest_autogen.egg-info/requires.txt
django_rest_autogen.egg-info/top_level.txt